<annotation>
	<folder/>
	<filename>car_510.jpeg</filename>
	<path>/home/sarvesh/project/LPRNet_Pytorch/data/LicensePlates/car_510.jpeg</path>
	<source>
		<database>Unknown</database>
	</source>
	<size>
		<width>590</width>
		<height>350</height>
		<depth>3</depth>
	</size>
	<segmented>0</segmented>
	<object>
		<name>license_plate</name>
		<pose>Unspecified</pose>
		<truncated>0</truncated>
		<difficult>0</difficult>
		<bndbox>
			<xmin>74</xmin>
			<ymin>132</ymin>
			<xmax>263</xmax>
			<ymax>173</ymax>
		</bndbox>
	</object>
</annotation>
