<annotation>
	<folder/>
	<filename>car_466.jpeg</filename>
	<path>/home/sarvesh/project/LPRNet_Pytorch/data/LicensePlates/car_466.jpeg</path>
	<source>
		<database>Unknown</database>
	</source>
	<size>
		<width>400</width>
		<height>225</height>
		<depth>3</depth>
	</size>
	<segmented>0</segmented>
	<object>
		<name>license_plate</name>
		<pose>Unspecified</pose>
		<truncated>0</truncated>
		<difficult>0</difficult>
		<bndbox>
			<xmin>253</xmin>
			<ymin>163</ymin>
			<xmax>284</xmax>
			<ymax>177</ymax>
		</bndbox>
	</object>
</annotation>
